statisticas/__init__.py
statisticas/med_disper.py
statisticas/med_tend_central.py
statisticas-0.0.3.dist-info/METADATA
statisticas-0.0.3.dist-info/WHEEL
statisticas-0.0.3.dist-info/top_level.txt
statisticas-0.0.3.dist-info/RECORD
