Metadata-Version: 2.1
Name: statisticas
Version: 0.0.3
Summary: The package has the purpose of help calculate statistics
Home-page: https://github.com/LucasMGuima/statisticas-package
Author: LucasMGuima
Author-email: lucasmguima@outlook.com
Requires-Python: >=3.8
